{"kgZQ+pykeXMN3EyzlLfXIQ==":"watermark2022-96x20.png","epHVCmUZNtSD2voWJTJQjA==":"watermark2022-460x94.png","tZyT6YbXwt5lPw0Um7N2xQ==":"ambiance-8550-2000x1333.jpg","5X2MxAZ/UOhb3tMr0U9xAA==":"ambiance-7858-1617x1078.jpg","N767+UgZYOxlsWb8hrQFPQ==":"ambiance-7251-1619x1079.jpg","/T9XSJoYvRKgtEhUB6UTwQ==":"img-7002-1632x1088.jpg","WQ2OKlReUlGkBsi2rEFISg==":"img-7162-2512x1675.jpg","MFxDrKBOvlzpuKOkN9/+mA==":"img-6984-2000x1333.jpg","6nWMpLmTS0ChzBMLDFGNQA==":"logo%20final(png)-240x99.png","QCLrdBVUS7YidYyWh6pS4g==":"scg%20png-240x71.png","dDcokT557wC6927RBL4q8A==":"ansi%20low%20res-240x31.png","osG8751MmkI4ECBY5e4qlw==":"untitled-1_vectorized-240x240.png"}